enotification/__init__.py
enotification/enotification.py
enotification-0.0.7.dist-info/LICENSE
enotification-0.0.7.dist-info/METADATA
enotification-0.0.7.dist-info/WHEEL
enotification-0.0.7.dist-info/top_level.txt
enotification-0.0.7.dist-info/RECORD
