Metadata-Version: 2.1
Name: enotification
Version: 0.0.7
Summary: A package to send an email when your function finished.
Home-page: https://github.com/DiamondI/enotification
Author: DiamondI
Author-email: 920076768@qq.com
License: UNKNOWN
Project-URL: Bug Tracker, https://github.com/DiamondI/enotification/issues
Platform: UNKNOWN
Classifier: Programming Language :: Python :: 3
Classifier: License :: OSI Approved :: MIT License
Classifier: Operating System :: OS Independent
Requires-Python: >=3.6
Requires-Dist: zmail
